<?xml version="1.0" encoding="windows-1251" ?>
<string_table>
#include "text\rus\string_table_amk_arts_desc.xml"
<string id="af_dummy_black_tip"><text>"Чёрная метка"</text></string>
<string id="af-ameba-mica"><text>"Слюда"</text></string>
<string id="af-ameba-slime"><text>"Слизь"</text></string>
<string id="af-ameba-slug"><text>"Слизняк"</text></string>
<string id="af-blood"><text>"Кровь камня"</text></string>
<string id="af-cristall"><text>"Кристалл"</text></string>
<string id="af-cristall-flower"><text>"Каменный цветок"</text></string>
<string id="af-drops"><text>"Капля"</text></string>
<string id="af-dummy-battery"><text>"Батарейка"</text></string>
<string id="af-dummy-dummy"><text>"Пустышка"</text></string>
<string id="af-dummy-glassbeads"><text>"Мамины бусы"</text></string>
<string id="af-dummy-pellicle"><text>"Плёнка"</text></string>
<string id="af-dummy-spring"><text>"Пружина"</text></string>
<string id="af-electra-flash"><text>"Вспышка"</text></string>
<string id="af-electra-moonlight"><text>"Лунный свет"</text></string>
<string id="af-electra-sparkler"><text>"Бенгальский огонь"</text></string>
<string id="af-fireball"><text>"Огненный шар"</text></string>
<string id="af-fuzz-kolobok"><text>"Колобок"</text></string>
<string id="af-gold-fish"><text>"Золотая рыбка"</text></string>
<string id="af-gravi"><text>"Грави"</text></string>
<string id="af-medusa"><text>"Медуза"</text></string>
<string id="af-mincer-meat"><text>"Ломоть мяса"</text></string>
<string id="af-night-star"><text>"Ночная звезда"</text></string>
<string id="af-rusty-kristall"><text>"Кристальная колючка"</text></string>
<string id="af-rusty-sea-urchin"><text>"Морской ёж"</text></string>
<string id="af-rusty-thorn"><text>"Колючка"</text></string>
<string id="af-soul"><text>"Душа"</text></string>
<string id="af-soul_new"><text>"Дирижабль"</text></string>
<string id="af_electra_blue"><text>"Лунный отблеск"</text></string>
<string id="af-vyvert"><text>"Выверт"</text></string>
<string id="Agroprom"><text>Агропром</text></string>
<string id="Ameba"><text>"Холодец"</text></string>
<string id="af-night_star_new"><text>"Одуванчик"</text></string>
<string id="af_dummy_fire"><text>"Пузырёк"</text></string>
<string id="Anomalies"><text>&#160;Аномалии</text></string>
<string id="Artifacts"><text>&#160;Артефакты</text></string>
<string id="Bald"><text>"Трамплин"</text></string>
<string id="Bar"><text>Бар</text></string>
<string id="Darkdolina"><text>Тёмная долина</text></string>
<string id="deadcity"><text>Иванковский райцентр</text></string>
<string id="k01_darkscape"><text>"Кишка" Зоны</text></string>
<string id="Electra"><text>"Электра"</text></string>
<string id="greedy"><text>"Жадинка"</text></string>
<string id="psi_field"><text>"Матрица"</text></string>
<string id="af_baloon"><text>"Баллончик"</text></string>


<string id="enc_zone_anomalies_greedy"><text>К сожалению в определениях данной аномалии, прозванной в сталкерском обиходе "Жадинкой", учёные ограничиваются лишь туманными гипотезами, самая популярная из которых гласит, что она является провалом в некое иное измерение, и материальные предметы из нашей вселенной подвергаются аннигиляции и превращению в питательную энергию. Но так как провал по настоящему небольшой (в метафизическом смысле), то целого сталкера протянуть сквозь это "игольное ушко" невозможно. Но сила втягивания довольно высока, поэтому ощущается так, как будто нечто держит его. Сброшенные предметы могут вызвать некоторый коллапс этого провала и выглядит это "насыщением" животной составляющей этой аномалии.</text></string>
<string id="enc_zone_anomalies_psi_field"><text>Образование, неясной до конца природы. При попадании сталкера в поле действия данной аномалии происходит тотальное изменения психофизической матрицы мозга. Сохраняются только основные двигательные и физиологические функции, практически человек превращается в так называемого "зомби". Лечению подобное поражение мозга не поддаётся.</text></string>
<string id="af_dummy_black_tip_desc"><text>Мифический артефакт. По рассказам, сталкер, получивший этот артефакт, не может от него сам избавиться, только отдать кому-либо другому. Судя по слухам, ни один сталкер, получивший этот артефакт, не прожил долго.</text></string>
<string id="enc_zone_anomalies_ameba"><text>Образование не ясной до конца природы. При контакте с телом наносит травмы, сходные с эффектом воздействия сильной кислоты. Образует три вида артефактов: "Слизь", "Слизняка", "Слюду".</text></string>
<string id="enc_zone_anomalies_bald"><text>Одна из первых зафиксированных аномалий. Наносит ударные повреждения переменным гравитационным полем. Результат встречи с "Трамплином" может быть разным - от небольших синяков и ушибов до мгновенной смерти. В дневное время достаточно легко обнаруживается по искажениям воздуха над аномалией и кружащейся листве. Фиксируется любыми видами детекторов, а также с помощью брошенных в неё различных предметов. Образует три вида артефактов: "Медузу", "Каменный цветок" и "Ночную звезду".</text></string>
<string id="enc_zone_anomalies_electra"><text>Аномальное образование диаметром около 3 метров, накапливающее статическое электричество. Потревоженная аномалия взрывается десятком мини-молний, разряжаясь на 2-3 секунд, причём поражение током для любого живого существа почти всегда смертельно. Характерной особенностью "Электры" является видимый над ней днём голубоватый туман. Обнаруживается любыми видами детекторов или с помощью бросания металлических предметов. Образует три вида артефактов: "Бенгальский огонь", "Вспышку" и "Лунный свет".</text></string>
<string id="enc_zone_anomalies_fuzz"><text>Аномально видоизменившаяся растительность. При быстром приближении живого существа выбрасывает облачко частиц, которые в случае контакта с открытой или слабо защищённой кожей серьёзно травмируют последнюю. На медленно движущиеся объекты не реагирует. Образует три вида артефактов (возможно, это семена): "Колючку", "Кристальную колючку", "Морского ежа".</text></string>
<string id="enc_zone_anomalies_gravi"><text>Аномалия предположительно гравитационной природы. В момент активизации со страшной силой втягивает в себя всё, что находится в радиусе 5-6 метров. При попадании в центр "Воронки" шансов выжить практически нет: тело и животного, и человека будет сжато в плотный комок, а затем разорвано в момент так называемой разрядки. Может быть обнаружена по характерному движению воздуха и втягивающейся в центр листве. Образует три вида артефактов: "Выверт", "Грави" и "Золотую рыбку".</text></string>
<string id="enc_zone_anomalies_lift"><text>Безвредная для здоровья гравитационная аномалия, позволяющая на некоторое время забыть о законах тяготения. В локальном объёме диаметром в несколько метров земное притяжения значительно снижено. Образует артефакт "Плёнка".</text></string>
<string id="enc_zone_anomalies_meat"><text>Название обусловлено эффектом поднятия в воздух любого живого существа с последующей раскруткой до огромной скорости. Природа "Карусели" пока не исследована до конца. Обнаруживается по лёгкому пылевому вихрю на расстоянии в 3-4 метра от земли. Очень важно не упустить момент начала втягивания в аномальный вихрь и не попасть в зону максимально сильного эффекта в центре - только тогда есть шанс отделаться минимальными травмами. Образует три вида артефактов: "Кровь камня", "Ломоть мяса" и "Душу".</text></string>
<string id="enc_zone_anomalies_radioactive"><text>Зона повышенного уровня - более 50 мкР/ч - радиации. Необходимо избегать длительного нахождения в подобных местах.</text></string>
<string id="enc_zone_anomalies_time"><text>Аномалию, которую по праву можно назвать маленьким чудом: в объёме диаметром в несколько метров течение времени многократно замедляется. Отрицательного воздействия на здоровье, судя по всему, не оказывает, но выбраться из неё нелегко. Интересно, что в центре "Машины времени" обычно находится артефакт "Мамины бусы", при изъятии которого аномалия прекращает своё существование.</text></string>
<string id="enc_zone_anomalies_zharka"><text>В неактивном состоянии выглядит как едва видимое облако горячего воздуха, однако при попадании в зону действия любого предмета или живого существа, образует конусообразный столп огня, температурой около 1500К. Образует три вида артефактов: "Капля", "Огненный шар" и "Кристалл".</text></string>
<string id="af_compass"><text>"Компас"</text></string>
<string id="af_compass_desc"><text>Редкий артефакт. Происхождение названия непонятно, данный артефакт не проявил свойств указывать куда-либо. Возможно, внешний вид (имеется несколько хаотично поворачивающихся образований, похожих на стрелки) напоминает морской компас. Взаимодействие активированного электроразрядом "Компаса" вызывает стимуляцию мышечной энергии носителя. При этом из-за сильного расхода калорий необходимо усиленное питание.</text></string>
<string id="af_electra_moonlight_new"><text>"Псевдо-свет"</text></string>
<string id="af_electra_moonlight_new_desc"><text>Ещё один артефакт напоминающий лунный свет, из-за чего так и был назван сталкерами. Где и как появляется - так до сих пор и не выяснено. Радиоактивен.</text></string>
<string id="af_electra_flash_new"><text>"Блик"</text></string>
<string id="af_electra_flash_new_desc"><text>Артефакт, который сталкеры путают с артефактом "Вспышка", поэтому и получил название "Блик". Радиоактивен.</text></string>
<string id="af_dummy_dummy_new"><text>"Изолятор"</text></string>
<string id="af_dummy_dummy_new_desc"><text>Очень редкая разновидность артефакта "Пустышка". По слухам, имеет какую-то особую защиту от электричества. Вредных воздействий от данного артефакта пока не наблюдалось.</text></string>
<string id="af_eye"><text>"Глаз"</text></string>
<string id="af_eye_desc"><text>%c[1,1,1,1]___%c[255,255,255,255]Доп. вес .................&#160;&#160;%c[255,1,255,1]+10 кг\n%c[default]"Глаз" - это артефакт, который появляется вблизи сдвоенных аномалий "Электра" и "Холодец". Свойства "Глаза" несколько различны для конкретных артефактов. Его активация позволяет несколько снизить гравитационную массу носителя.</text></string>
<string id="af_eye_desc_1"><text>%c[1,1,1,1]___%c[255,255,255,255]Доп. вес .................&#160;&#160;%c[255,1,255,1]+6 кг\n%c[default]"Глаз" - это артефакт, который появляется вблизи сдвоенных аномалий "Электра" и "Холодец". Свойства "Глаза" несколько различны для конкретных артефактов. Его активация позволяет несколько снизить гравитационную массу носителя.</text></string>
<string id="af_eye_desc_2"><text>%c[1,1,1,1]___%c[255,255,255,255]Доп. вес .................&#160;&#160;%c[255,1,255,1]+8 кг\n%c[default]"Глаз" - это артефакт, который появляется вблизи сдвоенных аномалий "Электра" и "Холодец". Свойства "Глаза" несколько различны для конкретных артефактов. Его активация позволяет несколько снизить гравитационную массу носителя.</text></string>
<string id="af_eye_desc_4"><text>%c[1,1,1,1]___%c[255,255,255,255]Доп. вес .................&#160;&#160;%c[255,1,255,1]+12 кг\n%c[default]"Глаз" - это артефакт, который появляется вблизи сдвоенных аномалий "Электра" и "Холодец". Свойства "Глаза" несколько различны для конкретных артефактов. Его активация позволяет несколько снизить гравитационную массу носителя.</text></string>
<string id="af_eye_desc_5"><text>%c[1,1,1,1]___%c[255,255,255,255]Доп. вес .................&#160;&#160;%c[255,1,255,1]+14 кг\n%c[default]"Глаз" - это артефакт, который появляется вблизи сдвоенных аномалий "Электра" и "Холодец". Свойства "Глаза" несколько различны для конкретных артефактов. Его активация позволяет несколько снизить гравитационную массу носителя.</text></string>
<string id="af_eye_desc_6"><text>Вырожденный артефакт "Глаз".</text></string>
<string id="af_battery"><text>"Прыгалка"</text></string>
<string id="af_battery_desc"><text>%c[1,1,1,1]___%c[255,255,255,255]Прыжок ..................&#160;&#160;%c[255,1,255,1]+10\n%c[default]"Прыгалка" - артефакт абсолютно непонятного принципа действия. "Прыгалка" преобразуется из обычной "Батарейки" в аномалии "Трамплин".</text></string>
<string id="af_battery_desc_6"><text>Вырожденный артефакт "Прыгалка".</text></string>
<string id="af_medusa_new"><text>"Медуза Горгона"</text></string>
<string id="af_medusa_new_desc"><text>Артефакт, внешне напоминающий обычную "Медузу". При каких обстоятельствах возникает - непонятно.</text></string>
<string id="af_flower_new"><text>"Пицца"</text></string>
<string id="af_flower_new_desc"><text>"Пицца", или как её ещё называют, "Яичница". Названа так из-за внешнего сходства с данными продуктами питания.</text></string>
<string id="af_glassbeads"><text>"Электробусы"</text></string>
<string id="af_glassbeads_desc"><text>"Электробусы" - артефакт, получаемый из нескольких ингредиентов прямой трансмутацией в аномалии "Снежная" (она же "Снежка", "Ледышка"). Помимо отличных показателей электрозащиты и пулестойкости, обладает уникальным свойством: при активации на поясе поглощает до половины урона при поднятии любого известного артефакта. Имеет очень высокую ценность при обмене.</text></string>
<string id="af_glassbeads_desc_6"><text>Вырожденный артефакт "Электробусы".</text></string>
<string id="af_crist_new"><text>"Призрачный кристалл"</text></string>
<string id="af_crist_new_desc"><text>Данный артефакт стал появляться в Зоне сравнительно недавно. Многие исследователи на основании этого факта создали теорию об эволюционировании Зоны как некоего "живого организма". По своим свойствам "Призрачный кристалл" близок к обычному "Кристаллу".</text></string>
<string id="capsule"><text>"Капсула артефакта"</text></string>
<string id="artifact_capsule"><text>Оболочка, внутри которой находится артефакт не менее чем третьего уровня.</text></string>
<string id="enc_zone_capsule"><text>Оболочка, внутри которой находится ценный артефакт. Пока не вскрыта оболочка, артефакт не проявляет своих свойств. К сожалению, капсулы очень радиоактивны.</text></string>
<string id="af_life_heart"><text>"Живое сердце"</text></string>
<string id="af_life_heart_desc"><text>nУникальный артефакт. Обладает поистине чудодейственным свойством воскрешать погибших. Единственный недостаток - большая тяжесть.</text></string>
<string id="af_medusa"><text>"Изумрудная медуза"</text></string>
<string id="af_green_medusa"><text>Уникальный артефакт, с виду обычная "Медуза", но зелёная. Совершенно не радиоактивная, излучает слабый свет. Существует мнение, что она появляется в результате совмещения двух аномалий - "Трамплина" и "Холодца".</text></string>
<string id="af_vyvert"><text>"Изумрудный выверт"</text></string>
<string id="af_green_vyvert"><text>Уникальный артефакт, с виду обычный "Выверт", но зелёный. Совершенно не радиоактивный, излучает слабый свет. Существует мнение, что он появляется в результате совмещения двух аномалий - "Воронки" и "Холодца".</text></string>
<string id="af_blood"><text>"Изумрудная кровь камня"</text></string>
<string id="af_green_blood"><text>Уникальный артефакт, с виду обычная "Кровь камня", но зелёная. Совершенно не радиоактивная, излучает слабый свет. Существует мнение, что она появляется в результате совмещения двух аномалий - "Карусели" и "Холодца".</text></string>
<string id="af_pellicle"><text>"Рубиновая плёнка"</text></string>
<string id="af_pellicle_red"><text>Уникальный артефакт, по виду напоминает обычную "Плёнку", но красного цвета. Возможно, трансмутируется из "Пленки" при попадании в аномалию "Снежная".</text></string>
<string id="af_dummy_spring"><text>"Рубиновая пружина"</text></string>
<string id="af_red_dummy_spring"><text>%c[1,1,1,1]___%c[255,255,255,255]Прыжок ..................&#160;&#160;%c[255,1,255,1]+8\n%c[default]Уникальный артефакт, по виду напоминает обычную "Пружину", но красного цвета. Возможно, трансмутируется при сверхнизких температурах из обычной "Пружины" в аномалии "Снежная".</text></string>
<string id="af_dummy_battery"><text>"Рубиновая батарейка"</text></string>
<string id="af_red_dummy_battery"><text>Уникальный артефакт, по виду напоминает обычную "Батарейку", но красного цвета. Возможно, трансмутируется при сверхнизких температурах из обычной "Батарейки" в аномалии "Снежная".</text></string>
<string id="enc_zone_artifact_af-ameba-mica"><text>Артефакт третьего уровня, по слухам образующийся в аномалии "Холодец". Цена высокая. Интерес к артефакту проявляют научные организации.</text></string>

<string id="artifact_af-ameba-mica"><text>%c[1,1,1,1]___%c[255,255,255,255]Пси-судорга ...........&#160;&#160;%c[255,1,255,1]-15%\n \n%c[default]Артефакт третьего уровня семейства аномалии "Холодец".</text></string>
<string id="artifact_af-ameba-mica_dyn1"><text>Артефакт третьего уровня семейства аномалии "Холодец".</text></string>
<string id="artifact_af-ameba-mica_dyn6"><text>Вырожденный артефакт третьего уровня семейства аномалии "Холодец".</text></string>
<string id="artifact_af-ameba-mica_dyn5"><text>%c[1,1,1,1]___%c[255,255,255,255]Пси-судорга ...........&#160;&#160;%c[255,1,255,1]-30%\n \n%c[default]Артефакт третьего уровня семейства аномалии "Холодец".</text></string>
<string id="enc_zone_artifact_af-ameba-slime"><text>Артефакт можно встретить рядом с аномалией "Холодец". Представляет собой полупрозрачное желеобразное образование. При ношении артефакта на поясе уменьшается вероятность потери большого количества крови при тяжёлых ранениях, но при этом увеличивается уязвимость к любым видам ожогов. Цена невысокая. Интерес к артефакту проявляют научные организации.</text></string>
<string id="artifact_af-ameba-slime_dyn1"><text>Артефакт первого уровня семейства аномалии "Холодец".</text></string>
<string id="artifact_af-ameba-slime_dyn6"><text>Вырожденный артефакт первого уровня семейства аномалии "Холодец".</text></string>
<string id="artifact_af-ameba-slime"><text>Артефакт первого уровня семейства аномалии "Холодец".</text></string>
<string id="artifact_af-ameba-slime_dyn4"><text>%c[1,1,1,1]___%c[255,255,255,255]Пси-судорга ...........&#160;&#160;%c[255,1,255,1]-15%\n \n%c[default]Артефакт первого уровня семейства аномалии "Холодец".</text></string>
<string id="enc_zone_artifact_af-ameba-slug"><text>Этот артефакт чаще всего находят возле аномалии "Холодец". Ношение этого полупрозрачного желеобразного образования на поясе уменьшает вероятность потери большого количества крови при тяжёлых ранениях, но делает человека уязвимым к любым видам ожогов. Цена средняя. Интерес к артефакту проявляют научные организации.</text></string>
<string id="artifact_af-ameba-slug_dyn1"><text>Артефакт второго уровня семейства аномалии "Холодец".</text></string>
<string id="artifact_af-ameba-slug_dyn6"><text>Вырожденный артефакт второго уровня семейства аномалии "Холодец".</text></string>
<string id="artifact_af-ameba-slug_dyn5"><text>%c[1,1,1,1]___%c[255,255,255,255]Пси-судорга ...........&#160;&#160;%c[255,1,255,1]-30%\n \n%c[default]Артефакт второго уровня семейства аномалии "Холодец".</text></string>
<string id="artifact_af-ameba-slug"><text>%c[1,1,1,1]___%c[255,255,255,255]Пси-судорга ...........&#160;&#160;%c[255,1,255,1]-15%\n \n%c[default]Артефакт второго уровня семейства аномалии "Холодец".</text></string>

<string id="enc_zone_artifact_af-blood"><text>Артефакт, образующийся в аномалии "Карусель". Представляет собой уродливое красноватое образование из спрессованных и причудливо изогнутых полимеризированных остатков растений, почвы, плоти и костей погибших сталкеров и мутантов. При ношении артефакта на поясе мистическим образом слегка ускоряется заживление ран. В то же время ухудшается устойчивость к физическим повреждениям. У сталкеров существует поверье, что в этом артефакте заключена сила погибших в аномалии людей. Цена продажи невысока по причине достаточно широкого распространения. Интерес к артефакту проявляют медики и всевозможные религиозные культы.</text></string>
<string id="artifact_af-blood"><text>Артефакт первого уровня семейства аномалии "Карусель".</text></string>
<string id="artifact_af-blood_dyn6d"><text>Вырожденный артефакт первого уровня семейства аномалии "Карусель".</text></string>
<string id="enc_zone_artifact_af-cristall"><text>Артефакт крайне редко можно найти рядом с аномалией "Жарка". Его название очень точно описывает форму артефакта – это большой переливающийся кристалл красноватого цвета. Сталкеры утверждают, что при его ношении значительно снижается уровень радиации в организме. Но, увы, артефакт не лучшим образом влияет на выносливость. Цена высокая. Интерес к артефакту проявляют научные организации.</text></string>
<string id="artifact_af-cristall"><text>Артефакт третьего уровня семейства аномалии "Жарка".</text></string>
<string id="artifact_af-cristall_dyn6d"><text>Вырожденный артефакт третьего уровня семейства аномалии "Жарка".</text></string>

<string id="enc_zone_artifact_af-drops"><text>Артефакт, появляющийся рядом с аномалией "Жарка". Каплевидное маленькое образование с потрескавшейся глянцевитой поверхностью. Сталкеры говорят, что при ношении этого артефакта снижается уровень радиации в организме, но за счёт сильного тепловыделения ухудшается выносливость. Цена невысокая. Интерес к артефакту проявляют коллекционеры и ювелиры.</text></string>
<string id="artifact_af-drops"><text>Артефакт первого уровня семейства аномалии "Жарка".</text></string>
<string id="artifact_af-drops_dyn6d"><text>Вырожденный артефакт первого уровня семейства аномалии "Жарка".</text></string>
<string id="enc_zone_artifact_af-dummy-battery"><text>Происхождение артефакта не известно. Ребристое блестящее образование. Очень полезный артефакт для его носителя. Улучшает все характеристики радиационной стойкости и восприимчивости к электричеству. Создаётся впечатление, что артефакт усиливает любые процессы, протекающие вокруг него. Цена продажи огромная. Особый интерес к артефакту проявляют научные организации.</text></string>
<string id="artifact_af-dummy-battery"><text>Артефакт семейства "Пустышка"</text></string>
<string id="enc_zone_artifact_af-dummy-dummy"><text>Происхождение артефакта не известно. Два жёстких диска, сцепленные вместе слизью. Артефакт слегка снижает поражение от всех типов гравитационных аномалий и взрывов, абсорбируя ударные волны. Цена продажи высокая. Интерес к артефакту проявляют научные организации.</text></string>
<string id="artifact_af-dummy-dummy"><text>Артефакт семейства "Пустышка"</text></string>
<string id="enc_zone_artifact_af-dummy-glassbeads"><text>Замечательный артефакт, берегите его. Он хорош тем, что имеет только положительные качества (уникальнейшее явление, так как только положительными свойствами, как правило, обладают абсолюты и редкие гипермодификаты). учёные ломают седые головы над тем, как подобные свойства можно получить в лабораторных условиях. Артефакт замедляет появление усталости и голода, приостанавливает кровотечения. Интерес к нему проявляют, пожалуй, все кому не лень.</text></string>
<string id="artifact_af-dummy-glassbeads"><text>Артефакт семейства "Пустышка"</text></string>
<string id="enc_zone_artifact_af-dummy-pellicle"><text>Этот артефакт настолько редок, что многие исследователи даже не догадываются, что такая субстанция может существовать в естественных условиях. Отторгает едкие химические компоненты.</text></string>
<string id="artifact_af-dummy-pellicle"><text>Артефакт семейства "Пустышка"</text></string>
<string id="enc_zone_artifact_af-dummy-spring"><text>Происхождение артефакта не известно. Представляет собой два жёстких диска, сцепленные вместе вязкой слизью. Он может самостоятельно перемещаться, совершая небольшие прыжки благодаря переменному гравитационному полю. При ношении на поясе снижает вероятность появления серьёзных травм в результате ударов. Цена продажи очень высокая. Интерес к артефакту проявляют научные организации.</text></string>
<string id="artifact_af-dummy-spring"><text>%c[1,1,1,1]___%c[255,255,255,255]Прыжок ..................&#160;&#160;%c[255,1,255,1]+10\n%c[default]Артефакт семейства "Пустышка"</text></string>
<string id="enc_zone_artifact_af-electra-flash"><text>Артефакт, образующийся в аномалии "Электра". Лёгкое полупрозрачное аморфное образование с бьющими изнутри лучиками света, редко испускающее вокруг себя маленькие искры. Ношение артефакта на поясе слегка увеличивает выносливость за счет увеличенного расхода калорий, что ведет к постоянному чувству голода, но при этом делает человека уязвимым к электричеству, науапливает радиацию. Цена высокая. Интерес к артефакту проявляют научные организации, коллекционеры и ювелиры.</text></string>
<string id="artifact_af-electra-flash"><text>Артефакт второго уровня семейства аномалии "Электра".\nСильно усиливает расход энергии человека.</text></string>
<string id="artifact_af-electra-flash_dyn6d"><text>Вырожденный артефакт второго уровня семейства аномалии "Электра".</text></string>
<string id="enc_zone_artifact_af-electra-moonlight"><text>Артефакт редко можно обнаружить около аномалии "Электра". Лёгкое полупрозрачное аморфное образование со светящейся сердцевиной, испускающее вокруг себя маленькие искры. Ношение артефакта на поясе значительно увеличивает выносливость, но из-за повышенного расхода энергии человеку необходимо есть значительно больше обычного. При попадании в аномалию "Электра" шансов на выживание у носящего этот артефакт человека остаётся минимум, накапливает радиацию. Цена очень высокая. Интерес к артефакту проявляют научные организации, коллекционеры и ювелиры.</text></string>
<string id="artifact_af-electra-moonlight"><text>Артефакт третьего уровня семейства аномалии "Электра".\nЗначительно усиливает расход энергии человека.</text></string>
<string id="artifact_af-electra-moonlight_dyn6d"><text>Вырожденный артефакт третьего уровня семейства аномалии "Электра".</text></string>
<string id="enc_zone_artifact_af-electra-sparkler"><text>Артефакт, образующийся в аномалии "Электра". Полупрозрачное аморфное очень лёгкое образование, редко испускающее вокруг себя маленькие искры. Ношение артефакта на поясе слегка увеличивает выносливость, но при этом делает человека уязвимым к электричеству и вызывает повышенное чувство голода, накапливает радиацию. Цена средняя. Интерес к артефакту проявляют научные организации, коллекционеры и ювелиры.</text></string>
<string id="artifact_af-electra-sparkler"><text>Артефакт первого уровня семейства аномалии "Электра".\nУвеличивает чувство голода.</text></string>
<string id="artifact_af-electra-sparkler_dyn6d"><text>Вырожденный артефакт первого уровня семейства аномалии "Электра".</text></string>
<string id="enc_zone_artifact_af-fireball"><text>Артефакт чаще всего находят возле аномалии "Жарка". Полупрозрачное красноватое образование шаровидной формы. Сталкеры говорят, что ношение артефакта снижает уровень радиации в организме. Но за счёт сильного тепловыделения ухудшается выносливость. Цена средняя. Интерес к артефакту проявляют коллекционеры и ювелиры.</text></string>
<string id="artifact_af-fireball"><text>Артефакт второго уровня семейства аномалии "Жарка".</text></string>
<string id="artifact_af-fireball_6"><text>Вырожденный артефакт второго уровня семейства аномалии "Жарка".</text></string>
<string id="enc_zone_artifact_af-fuzz-kolobok"><text>Артефакт неизвестного происхождения. учёные до сих пор не могут разгадать рецепт получения этого чуда Зоны. При ношении на поясе значительно увеличивается стойкость организма к любым физическим повреждениям. Радиоактивен. Цена очень высокая. Особый интерес к артефакту проявляют медики.</text></string>
<string id="artifact_af-fuzz-kolobok"><text>Артефакт семейства "пустышка".</text></string>
<string id="enc_zone_artifact_af-gold-fish"><text>Артефакт, крайне редко появляющийся в аномалии "Воронка". Красивое образование с зеркальной поверхностью. Ночью освещает пространство вокруг себя в радиусе 1-2 метров. Представляет собой спрессованный и причудливо изогнутый сильной гравитацией металл со смесью всего, что вообще попадает в аномалию в момент разрядки. Сильно радиактивен. Способен генерировать вокруг себя антигравитационное поле, которое локально снижает воздействие силы притяжения. Широко применяется сталкерами для снижения веса переносимого в рюкзаке груза..  Цена продажи очень высокая. Интерес к артефакту проявляют научные организации, коллекционеры и ювелиры.</text></string>
<string id="artifact_af-gold-fish"><text>%c[1,1,1,1]___%c[255,255,255,255]Доп. вес .................&#160;&#160;%c[255,1,255,1]+8 кг\n%c[default]Артефакт третьего уровня семейства аномалии "Воронка".</text></string>
<string id="artifact_af-gold-fish_dyn1d"><text>Артефакт третьего уровня семейства аномалии "Воронка".</text></string>
<string id="artifact_af-gold-fish_dyn6d"><text>Вырожденный артефакт третьего уровня семейства аномалии "Воронка".</text></string>
<string id="artifact_af-gold-fish_dyn2d"><text>%c[1,1,1,1]___%c[255,255,255,255]Доп. вес .................&#160;&#160;%c[255,1,255,1]+8 кг\n%c[default]Артефакт третьего уровня семейства аномалии "Воронка".</text></string>
<string id="artifact_af-gold-fish_dyn4d"><text>%c[1,1,1,1]___%c[255,255,255,255]Доп. вес .................&#160;&#160;%c[255,1,255,1]+12 кг\n%c[default]Артефакт третьего уровня семейства аномалии "Воронка".</text></string>
<string id="enc_zone_artifact_af-gravi"><text>Красивый артефакт, образующийся в аномалии "Воронка". Представляет собой спрессованные и причудливо изогнутые сильной гравитацией остатки растений, почвы и вообще всего, что попадает в непосредственную близость аномалии. Радиактивен. Способен поддерживать небольшое антигравитационное поле вокруг себя. Многие сталкеры используют его, чтобы значительно уменьшить вес своего рюкзака. . Цена продажи и вероятность появления средняя. Интерес к артефакту проявляют научные организации, коллекционеры и ювелиры.</text></string>
<string id="artifact_af-gravi"><text>%c[1,1,1,1]___%c[255,255,255,255]Доп. вес .................&#160;&#160;%c[255,1,255,1]+4 кг\n%c[default]Артефакт второго уровня семейства аномалии "Воронка".</text></string>
<string id="artifact_af-gravi_dyn1d"><text>Артефакт второго уровня семейства аномалии "Воронка".</text></string>
<string id="artifact_af-gravi_dyn6d"><text>Вырожденный артефакт второго уровня семейства аномалии "Воронка".</text></string>
<string id="artifact_af-gravi_dyn2d"><text>%c[1,1,1,1]___%c[255,255,255,255]Доп. вес .................&#160;&#160;%c[255,1,255,1]+4 кг\n%c[default]Артефакт второго уровня семейства аномалии "Воронка".</text></string>
<string id="artifact_af-gravi_dyn4d"><text>%c[1,1,1,1]___%c[255,255,255,255]Доп. вес .................&#160;&#160;%c[255,1,255,1]+8 кг\n%c[default]Артефакт второго уровня семейства аномалии "Воронка".</text></string>
<string id="enc_zone_artifact_af-medusa"><text>Артефакт, образующийся в аномалии "Трамплин". Представляет собой спрессованные и причудливо изогнутые сильной гравитацией остатки растений и листвы. При ношении артефакта на поясе увеличивается иммунитет к воздействию гравитационных аномалий, таких как "Холодец" , а также проявляется незначительный эффект защитного поля, снижающего поражение от стрелкового оружия. Выводит пси. Слегка радиоактивен. Цена продажи невысока по причине достаточно широкого распространения. Интерес к артефакту проявляют научные организации.</text></string>
<string id="artifact_af-medusa_dyn1d"><text>Артефакт первого уровня семейства аномалии "Трамплин".</text></string>
<string id="artifact_af-medusa_dyn6d"><text>Вырожденный артефакт первого уровня семейства аномалии "Трамплин".</text></string>
<string id="artifact_af-medusa_dyn3d"><text>Артефакт первого уровня семейства аномалии "Трамплин".</text></string>
<string id="artifact_af-medusa"><text>Артефакт первого уровня семейства аномалии "Трамплин".</text></string>
<string id="enc_zone_artifact_af-night-star"><text>Артефакт, крайне редко образующийся в аномалии "Трамплин". Красивое образование с зеркальной поверхностью и цветными фосфорицирующими вкраплениями. Ночью освещает зеленоватым светом всё вокруг себя в радиусе 1-2 метров, за что и получил у сталкеров такое название. Представляет собой спрессованные и причудливо изогнутые сильной гравитацией остатки растений, почвы и вообще всего, что попадает в непосредственную близость аномалии. При ношении артефакта на поясе сильно увеличивается иммунитет к воздействию гравитационных аномалий, таких как "Холодец", а также проявляется эффект защитного поля, снижающего поражение от стрелкового оружия. Но при этом артефакт сильно радиоактивен, поэтому долгое ношение противопоказано. Цена продажи очень высокая. Интерес к артефакту проявляют научные организации и военные.</text></string>
<string id="artifact_af-night-star"><text>Артефакт третьего уровня семейства аномалии "Трамплин".</text></string>
<string id="artifact_af-night-star_dyn3d"><text>Артефакт третьего уровня семейства аномалии "Трамплин".</text></string>
<string id="artifact_af-night-star_dyn1d"><text>Артефакт третьего уровня семейства аномалии "Трамплин".</text></string>
<string id="artifact_af-night-star_dyn6d"><text>Вырожденный артефакт третьего уровня семейства аномалии "Трамплин".</text></string>
<string id="enc_zone_artifact_af-cristall-flower"><text>Рождается в аномалии "Трамплин". Такой артефакт можно найти в немногих районах Зоны. Вкрапления металлических соединений дают красивую игру света. Рассматривание этого артефакта вблизи костра ночью замечательно успокаивает.</text></string>
<string id="artifact_af-cristall-flower"><text>Артефакт второго уровня семейства аномалии "Трамплин".</text></string>
<string id="artifact_af-cristall-flower_dyn3d"><text>Артефакт второго уровня семейства аномалии "Трамплин".</text></string>
<string id="artifact_af-cristall-flower_dyn1d"><text>Артефакт второго уровня семейства аномалии "Трамплин".</text></string>
<string id="artifact_af-cristall-flower_dyn6d"><text>Вырожденный артефакт второго уровня семейства аномалии "Трамплин".</text></string>
<string id="enc_zone_artifact_af-mincer-meat"><text>Артефакт, образующийся в аномалии "Карусель". Представляет собой уродливое желтоватое образование из спрессованных и причудливо изогнутых полимеризированных остатков плоти и костей погибших существ. При ношении артефакта на поясе мистическим образом слегка ускоряется процесс заживления ран, и останавливаются кровотечения. У сталкеров существует поверье, что в этом артефакте заключена сила погибших в аномалии людей. В то же время ухудщается устойчивость к физическим повреждениям. Цена продажи и вероятность появления средняя. Интерес к артефакту проявляют медики и всевозможные религиозные культы.</text></string>
<string id="artifact_af-mincer-meat"><text>Артефакт второго уровня семейства аномалии "Карусель".</text></string>
<string id="artifact_af-mincer-meat_6"><text>Вырожденный артефакт второго уровня семейства аномалии "Карусель".</text></string>

<string id="enc_zone_artifact_af-rusty-kristall"><text>Артефакт можно найти рядом с аномалией "Ржавые волосы". Он выводит радиацию из организма человека и увеличивает высоту прыжка, но в то же время открывает кровотечения, так что при ношением этого артефакта надо быть осторожным и не забывать о его отрицательном воздействии. Цена средняя. Интерес к артефакту проявляют научные организации, коллекционеры и ювелиры.</text></string>
<string id="artifact_af-rusty-kristall"><text>%c[1,1,1,1]___%c[255,255,255,255]Прыжок ..................&#160;&#160;%c[255,1,255,1]+3\n%c[default]Артефакт второго уровня семейства аномалии "Ржавые волосы". Увеличивает высоту прыжка.</text></string>
<string id="artifact_af-rusty-kristall_1"><text>Артефакт второго уровня семейства аномалии "Ржавые волосы".</text></string>
<string id="artifact_af-rusty-kristall_6"><text>Вырожденный артефакт второго уровня семейства аномалии "Ржавые волосы".</text></string>
<string id="artifact_af-rusty-kristall_5"><text>%c[1,1,1,1]___%c[255,255,255,255]Прыжок ..................&#160;&#160;%c[255,1,255,1]+4\n%c[default]Артефакт второго уровня семейства аномалии "Ржавые волосы". Увеличивает высоту прыжка.</text></string>
<string id="enc_zone_artifact_af-rusty-sea-urchin"><text>Артефакт чаще всего находят неподалёку от аномалии "Ржавые волосы". Он выводит радиацию из организма человека и увеличивает высоту прыжка. Однако при постоянном использовании этого артефакта у человека появляется риск потери большого количества крови. Цена высокая. Интерес к артефакту проявляют научные организации, коллекционеры и ювелиры.</text></string>
<string id="artifact_af-rusty-sea-urchin"><text>%c[1,1,1,1]___%c[255,255,255,255]Прыжок ..................&#160;&#160;%c[255,1,255,1]+4\n%c[default]Артефакт третьего уровня семейства аномалии "Ржавые волосы". Увеличивает высоту прыжка.</text></string>
<string id="artifact_af-rusty-sea-urchin_1"><text>Артефакт третьего уровня семейства аномалии "Ржавые волосы".</text></string>
<string id="artifact_af-rusty-sea-urchin_6"><text>Вырожденный артефакт третьего уровня семейства аномалии "Ржавые волосы".</text></string>
<string id="artifact_af-rusty-sea-urchin_5"><text>%c[1,1,1,1]___%c[255,255,255,255]Прыжок ..................&#160;&#160;%c[255,1,255,1]+6\n%c[default]Артефакт третьего уровня семейства аномалии "Ржавые волосы". Увеличивает высоту прыжка.</text></string>
<string id="enc_zone_artifact_af-rusty-thorn"><text>Артефакт очень часто можно обнаружить возле аномалии "Ржавые волосы". Он выводит радиацию из организма человека и увеличивает высоту прыжка.. Однако у людей с ослабленным иммунитетом артефакт также вызывает сильные кровотечения. Цена низкая. Интерес к артефакту проявляют научные организации, коллекционеры и ювелиры.</text></string>
<string id="artifact_af-rusty-thorn"><text>%c[1,1,1,1]___%c[255,255,255,255]Прыжок ..................&#160;&#160;%c[255,1,255,1]+2\n%c[default]Артефакт первого уровня семейства аномалии "Ржавые волосы". Увеличивает высоту прыжка.</text></string>
<string id="artifact_af-rusty-thorn_1"><text>Артефакт первого уровня семейства аномалии "Ржавые волосы".</text></string>
<string id="artifact_af-rusty-thorn_6"><text>Вырожденный артефакт первого уровня семейства аномалии "Ржавые волосы".</text></string>
<string id="artifact_af-rusty-thorn_2"><text>%c[1,1,1,1]___%c[255,255,255,255]Прыжок ..................&#160;&#160;%c[255,1,255,1]+2\n%c[default]Артефакт первого уровня семейства аномалии "Ржавые волосы". Увеличивает высоту прыжка.</text></string>
<string id="artifact_af-rusty-thorn_5"><text>%c[1,1,1,1]___%c[255,255,255,255]Прыжок ..................&#160;&#160;%c[255,1,255,1]+3\n%c[default]Артефакт первого уровня семейства аномалии "Ржавые волосы". Увеличивает высоту прыжка.</text></string>
<string id="enc_zone_artifact_af-soul"><text>Очень редкий артефакт, образующийся в аномалии "Карусель". Представляет собой желтовато-красное блестящее образование из спрессованных и причудливо изогнутых полимеризированных остатков живой свежей плоти. У сталкеров существует поверье, что в этом артефакте заключены души погибших в аномалии людей. При ношении артефакта на поясе мистическим образом в течение нескольких секунд полностью восстанавливается здоровье, и останавливаются любые кровотечения. В то же время значительно ухудшается устойчивость к физическим повреждениям. Также сталкеры отмечают забавный факт – когда носишь на поясе этот артефакт, постоянно хочется есть. Цена продажи очень высокая. В основном артефакт появляется в аномалиях, поглощающих большое число органических объектов. Интерес к артефакту проявляют медики и всевозможные религиозные культы.</text></string>
<string id="artifact_af-soul"><text>Артефакт третьего уровня семейства аномалии "Карусель".</text></string>
<string id="artifact_af-soul_dyn6d"><text>Вырожденный артефакт третьего уровня семейства аномалии "Карусель".</text></string>
<string id="af_electra_blue_desc"><text>Редкий артефакт чем то напоминающий Лунный свет.</text></string>
<string id="enc_zone_artifact_af-soul_new"><text>Очень редкий артефакт, образующийся у аномалии пространственного прокола, именуемой в среде сталкеров "Жадинка". </text></string>
<string id="artifact_af-soul_new"><text>%c[1,1,1,1]___%c[255,255,255,255]Доп. вес .................&#160;&#160;%c[255,1,255,1]+24 кг\n%c[default]Очень редкий артефакт, образующийся у аномалии пространственного прокола, именуемой в среде сталкеров "Жадинка"</text></string>
<string id="enc_zone_artifact_af-vyvert"><text>Артефакт, образующийся в аномалии "Воронка". Представляет собой спрессованные и причудливо изогнутые сильной гравитацией остатки растений, почвы и остальных мелких обьектов, что попадают в непосредственную близость аномалии. Слабо радиоактивен. Способен поддерживать небольшое антигравитационное поле вокруг себя. Многие сталкеры используют его, чтобы немного уменьшить вес своего рюкзака. Цена продажи невысока по причине достаточно широкого распространения. Интерес к артефакту проявляют научные организации и частные коллекционеры.</text></string>
<string id="artifact_af-vyvert"><text>%c[1,1,1,1]___%c[255,255,255,255]Доп. вес .................&#160;&#160;%c[255,1,255,1]+2 кг\n%c[default]Артефакт первого уровня семейства аномалии "Воронка".</text></string>
<string id="artifact_af-vyvert_dyn1d"><text>Артефакт первого уровня семейства аномалии "Воронка".</text></string>
<string id="artifact_af-vyvert_dyn6d"><text>Вырожденный артефакт первого уровня семейства аномалии "Воронка".</text></string>
<string id="artifact_af-vyvert_dyn2d"><text>%c[1,1,1,1]___%c[255,255,255,255]Доп. вес .................&#160;&#160;%c[255,1,255,1]+2 кг\n%c[default]Артефакт первого уровня семейства аномалии "Воронка".</text></string>
<string id="artifact_af-vyvert_dyn4d"><text>%c[1,1,1,1]___%c[255,255,255,255]Доп. вес .................&#160;&#160;%c[255,1,255,1]+4 кг\n%c[default]Артефакт первого уровня семейства аномалии "Воронка".</text></string>

<string id="af_ice_desc"><text>Чрезвычайно интересный для науки артефакт. Славится тем, что вытягивает практически любую энергию из окружающих объектов - кинетическую, тепловую, и даже разряжает аккумуляторы в устройствах. Чем выше энергия, тем больше он её забирает. Сам по себе, редко имеет температуру выше нуля градусов и стремится охладить все неживые объекты в радиусе метра. Для учёных до сих пор остаётся загадкой, куда он девает поглощённую энергию. Стоит дорого.</text></string>
<string id="af_ice_desc_6"><text>Вырожденный артефакт "Мороженое".</text></string>
<string id="af-night_star_new_desc"><text>Артефакт, который проявляет свойство, которое совершенно не понятно по своим физическим принципам - при активации воздух окружающий носителя, приобретает очень сильную вязкость (Из-за этого свойства в среде сталкеров этот артефакт часто называют также - "Парашют")... Благодаря этому при использовании этого артефакта якобы можно прыгнуть с большой высоты без особых повреждений.</text></string>
<string id="af_dummy_fire_desc"><text>Странный артефакт. Вроде нет никаких свойств при стимуляции. Продавать или нет, самому решать...</text></string>
<string id="af_baloon_desc"><text>Ещё одна бесполезная, но красивая штучка. Странный артефакт. Вроде нет никаких свойств при стимуляции. Продавать или нет, самому решать...</text></string>
<string id="af_ice"><text>"Мороженое"</text></string>
<string id="enc_zone_artifact_af_unknown_1"><text>Аномальное образование A-239.</text></string>
<string id="enc_zone_artifact_af_unknown_2"><text>Аномальное образование B-274.</text></string>
<string id="enc_zone_artifact_af_unknown_3"><text>Аномальное образование C-247.</text></string>
<string id="enc_zone_artifact_af_unknown_4"><text>Аномальное образование D-845.</text></string>
<string id="enc_zone_artifact_af_unknown_5"><text>Аномальное образование D-396.</text></string>
<string id="enc_zone_artifact_af_unknown_6"><text>Аномальное образование D-654.</text></string>
<string id="enc_zone_artifact_af_unknown_7"><text>Аномальное образование D-781.</text></string>
<string id="enc_zone_artifact_af_unknown_8"><text>Аномальное образование E-545.</text></string>
<string id="enc_zone_artifact_af_unknown_9"><text>Аномальное образование G-024.</text></string>
<string id="enc_zone_artifact_af_unknown_10"><text>Аномальное образование H-121.</text></string>
<string id="enc_zone_artifact_af_unknown_11"><text>Аномальное образование I-182.</text></string>
<string id="enc_zone_artifact_af_unknown_12"><text>Аномальное образование J-244.</text></string>
<string id="enc_zone_artifact_af_unknown_13"><text>Аномальное образование J-142.</text></string>
<string id="enc_zone_artifact_af_unknown_14"><text>Аномальное образование J-060.</text></string>
<string id="enc_zone_artifact_af_unknown_15"><text>Аномальное образование J-790.</text></string>
<string id="enc_zone_artifact_af_unknown_16"><text>Аномальное образование K-346.</text></string>
<string id="enc_zone_artifact_af_unknown_17"><text>Аномальное образование K-162.</text></string>
<string id="enc_zone_artifact_af_unknown_18"><text>Аномальное образование K-683.</text></string>
<string id="enc_zone_artifact_af_unknown_19"><text>Аномальное образование L-614.</text></string>
<string id="enc_zone_artifact_af_unknown_20"><text>Аномальное образование M-609.</text></string>
<string id="enc_zone_artifact_af_unknown_21"><text>Аномальное образование N-766.</text></string>
<string id="enc_zone_artifact_af_unknown_22"><text>Аномальное образование O-477.</text></string>
<string id="enc_zone_artifact_af_unknown_23"><text>Аномальное образование P-049.</text></string>
<string id="enc_zone_artifact_af_unknown_24"><text>Аномальное образование P-877.</text></string>
<string id="enc_zone_artifact_af_unknown_25"><text>Аномальное образование P-702.</text></string>
<string id="enc_zone_artifact_af_unknown_26"><text>Аномальное образование Q-317.</text></string>
<string id="enc_zone_artifact_af_unknown_27"><text>Аномальное образование R-051.</text></string>
<string id="enc_zone_artifact_af_unknown_28"><text>Аномальное образование S-804.</text></string>
<string id="enc_zone_artifact_af_unknown_29"><text>Аномальное образование S-237.</text></string>
<string id="enc_zone_artifact_af_unknown_30"><text>Аномальное образование S-357.</text></string>
<string id="enc_zone_artifact_af_unknown_31"><text>Аномальное образование S-753.</text></string>
<string id="enc_zone_locations_agroprom"><text>Странная местность. Если углубиться в неё, то выйдешь на сильно загрязнённую радиацией равнину. Расположенное там мелкое озеро до краёв забито обломками техники. Ещё можно посетить старый институт и завод, однако в последнее время там что-то слишком часто стали мелькать военные.</text></string>
<string id="enc_zone_locations_bar"><text>Группировка "Долг" расчистила на окраине Дикой территории местечко себе под базу и позволяет сталкерам здесь отдохнуть. Своего рода оазис в пустыне: ни аномалий, ни мутантов. Есть подземелье, в котором разместился бар "100 рентген". В нём собираются сталкеры со всей Зоны. Заправляет в баре местный торговец, так что здесь можно не только пообщаться, но и продать-купить почти всё, что угодно. На севере от бара находится военная база, на юге - Свалка.</text></string>
<string id="enc_zone_locations_darkdolina"><text>Здесь всегда мрачно и туманно, часто идёт дождь. В Тёмной долине можно разжиться неплохими артефактами, а можно и быстро распрощаться с жизнью. Здесь много матёрых сталкеров. Они пришли сюда за ценными артефактами, но есть и бандиты. Можно поискать вход в расположенную где-то здесь подземную лабораторию, только оттуда никто не возвращался, и что там прячется, никому как следует не известно.</text></string>
<string id="enc_zone_locations_escape"><text>Своего рода предбанник Зоны, первое место, куда попадают новички, обживаясь понемногу. В погребе за деревенькой возле армейского блокпоста обитает торговец - с ним полезно потолковать. Соваться на блокпост и попадаться на глаза солдатам не резон: у них приказ стрелять без предупреждения; с другой стороны, некоторые за деньги готовы мгновенно подобреть, особенно если рядом нет начальства. Убивать солдат очень не рекомендуется, разве только в случае прямой угрозы для жизни.</text></string>
<string id="enc_zone_locations_garbage"><text>Огромное техническое кладбище: сюда ещё после первой аварии свезли горы радиоактивного хлама. Есть остатки старых построек, встречаются мутанты. Здесь, как и у самого периметра, много новичков, а рядом крутятся бандиты, всегда ищущие кусок пожирнее и чтобы без особых хлопот. Можно найти немного артефактов, но лучше надолго не задерживаться - есть места и поинтереснее. Если идти на север, то выйдешь к Дикой территории; на западе - проход в Тёмную долину; на востоке - дорога к НИИ "Агропром".</text></string>
<string id="enc_zone_locations_military-loc"><text>Заброшенная армейская база рядом с деревенькой, в которой обитают странные существа, и небольшим болотцем. В деревню редко сталкеры суются, чаще обходят десятой дорогой. А на территории военной базы анархисты из группировки "Свобода" обосновались. Если дальше в Зону от базы идти, то попадёшь прямо к "Выжигателю мозгов". Он путь к Припяти и ЧАЭС наглухо перекрывает.</text></string>
<string id="enc_zone_locations_pripiat"><text>Это был город энергетиков. Его построили ещё вместе с ЧАЭС. Немаленький был городок... Только теперь там уже никто не живёт, кроме, конечно, нечисти всякой, вроде мутантов и зомби. Пройти туда, судя по всему, и вовсе нельзя. "Выжигатель мозгов" путь закрывает.</text></string>
<string id="enc_zone_locations_radar"><text>Страшное место. Тут ни за здорово живёшь сгинуть можно, даже если перед этим всю жизнь везунчиком был. Любой, кто к "Выжигателю мозгов" близко подойдёт, с ума сходит, в зомби превращается и бродит потом по Зоне, неприкаянный. Одни оболочки от людей остаются, и никто оттуда с своём уме не возвращался.</text></string>
<string id="enc_zone_locations_rostok"><text>На Дикой территории раньше довольно крупный завод был, от которого теперь остались одни руины. В них нашли свой конец много сталкеров: развелось там нечисти всякой, словно сходится она туда со всей Зоны. По слухам, правда, что-то очень важное на этом заводе есть, так что желающих попытать счастья всегда в достатке.</text></string>
<string id="enc_zone_locations_stancia"><text>Бывшая атомная станция, о которой хоть раз слышал каждый. Это самое сердце Зоны. Если верить легендам, где-то там находится некая штука, способная выполнить любое желание - её называют Монолитом.</text></string>
<string id="enc_zone_locations_yantar"><text>Легендарное озеро в одноимённом секторе давно уже высохло, одно мелкое болотце осталось. Ходить туда особенно опасно потому, что любой, кто слишком далеко сунется, сразу же умом повреждается. А по всему сектору зомби бродят и если кого увидят, так к нему идут совсем не с мирными намерениями. Если обойти озеро и группы зомби, то попадётся научный лагерь. Там учёные - их вертолётами доставили - изучают что-то. С ними потолковать можно, они артефакты покупают, даже задание какое-нибудь дать могут.</text></string>
<string id="enc_zone_zone-story_story-2006"><text>Зона отчуждения осветилась ярчайшим, почти нестерпимым светом, и было видно, как на небе начинают испаряться облака. После мгновения полной тишины пришёл грохот и землетрясение. Люди падали на землю, зажимая глаза и уши; кто мог, тот бежал, спасая свою жизнь. Со стороны это выглядело так, будто всё похороненное под саркофагом ядерное топливо разом взлетело на воздух. Через сутки правительственные войска уже полностью оцепили новую Зону. С помощью спутников удалось выяснить, что эпицентр взрыва находился не у блоков самой АЭС, а в километре от них. Считается, что весь персонал станции погиб сразу же, однако внутри кольца оцепления осталось много других людей. Организовать спасательные операции не представлялось возможным, поскольку отряды людей и техники, посланные вглубь поражённой территории, почти сразу же погибали. Через некоторое время после аварии диаметр Зоны скачкообразно возрос на несколько километров. Большая часть правительственных войск, охранявших периметр, и находившихся там научных лабораторий мгновенно погибли. Началась паника; жители окрестных сёл и городов были в спешке эвакуированы или бежали сами. Над миром нависла опасность, о размерах которой до сих пор можно только гадать.</text></string>
<string id="enc_zone_zone-story_story-2008"><text>Прошло два года с тех пор, как случилась жуткая катастрофа в Зоне отчуждения вокруг Чернобыльской АЭС. Большое количество погибших и пропавших без вести людей, павший скот, почерневшие постройки, изувеченный лес... учёные до сих пор не могут дать объяснений случившемуся. А Зона, внутри которой были обнаружены совершенно фантастические аномалии, тем временем растёт. Редкие экспедиции сталкиваются с мутировавшими видами животных, обладающих удивительными особенностями.</text></string>
<string id="enc_zone_zone-story_story-2010"><text>По следам отчаянных одиночек-сталкеров за широкомасштабное изучение Зоны опять берутся научные экспедиции. Однако внутри охраняемого армией периметра уже имеется множество "неучтённых лиц", вплоть до браконьеров и бандитов. В основной своей массе сталкеры путешествуют по Зоне в поисках разнообразных аномальных образований, так называемых артефактов, за которые нередко выручают неплохие деньги.</text></string>
<string id="enc_zone_zone-story_story-raid"><text>Армейские подразделения, в том числе и специального назначения, возглавляемые отрядами военных сталкеров, предприняли крупную экспедицию внутрь Зоны с целью прорваться к ЧАЭС и уничтожить предполагаемую причину возникновения смертельных аномальных полей либо наконец-то добыть достоверную информацию о происходящих там процессах. Данное предприятие, в котором принимали участие более тысячи человек и множество техники, полностью провалилось. Отдельные группы уцелевших осели на территории Зоны без особых надежд на спасение.</text></string>
<string id="Escape"><text>Кордон</text></string>
<string id="Fuzz"><text>"Жгучий пух"</text></string>
<string id="Garbage"><text>Свалка</text></string>
<string id="Gravi"><text>"Воронка"</text></string>
<string id="Lift"><text>"Лифт"</text></string>
<string id="Locations"><text>&#160;Территории</text></string>
<string id="Meat"><text>"Карусель"</text></string>
<string id="Military-loc"><text>Армейская база</text></string>
<string id="Pripiat"><text>Припять</text></string>
<string id="Radar"><text>"Выжигатель"</text></string>
<string id="Radioactive"><text>Очаг радиоактивности</text></string>
<string id="Rostok"><text>Дикая территория</text></string>
<string id="Stancia"><text>ЧАЭС</text></string>
<string id="Story-2006"><text>2008 год, 12 апреля, 14:33</text></string>
<string id="Story-2008"><text>2010 год</text></string>
<string id="Story-2010"><text>2011 год</text></string>
<string id="Story-raid"><text>Прорыв в Зону. 2011 год</text></string>
<string id="Time_machine"><text>"Машина времени"</text></string>
<string id="Yantar"><text>Янтарь</text></string>
<string id="Zharka"><text>"Жарка"</text></string>
<string id="Zone"><text>Зона</text></string>
<string id="Zone-story"><text>&#160;Информация о Зоне</text></string>
<string id="enc_many_in_zone"><text>О валюте в ЗОНЕ</text></string>
<string id="enc_many_in_zone_text"><text>Сидорович:\nРубли, мда... Советские... Смотрю на них и детство вспоминаю. Хорошее было время. Беззаботное. Газвода за копейку. Мороженное за 10.\nКак оно получилось что мы тут ими расплачиваться стали? Смотри сам...\nКогда бахнуло то второй раз и ЗОНА образовалась нашлись смельчаки, которые стали сюда тайком пробираться - вояки то обложили её со всех сторон крепко накрепко, всё думали: вот вот какая-нибудь зараза и чудовища полезут.\nНу так, а сталкеры, самые первые значит, ночами ползком пробирались внутрь и выносили всякие диковинки - "артефакты". Образовался небольшой бизнес по доставке этих артов заказчикам. Сталкеры тогда получали полновесные кровно заработанные доллары, ну или другую валюту.\nПотом наиболее смелые, да что там, скажем прямо - отчаянные люди, поняли, что по одному артефакту таскать очень накладно. Ведь возвращались хорошо если два из пяти ушедших в ЗОНУ, да и те, часто с пустыми руками были. В общем мы, да да, я тоже.. кхе... молодость блин... Решили мы, что сталкеров нужно поддержать тут, внутри ЗОНЫ. Еды там подкинуть, патронов, снаряжения... Ну всяко разно. Вот.\nА доллары или другие какие полновесные тугрики сюда тянуть опасно, народец то сюда прёт всё больше шалый, отмороженный, те, кому и терять то нечего. Такие не то что за десяток баксов, иной раз и за батон колбасы пристрелить могут! \nКак быть спрашиваешь? Случай помог, по большому счету. Пара сталкеров нашли в одном из разрушенных посёлков банковское хранилище. Ну брошенные ещё после первого выселения старые советские рубли. Много не много, но эти, никому не нужные на большой земле бумажки, мы стали применять для расчётов тут, в ЗОНЕ. Поначалу только ими и рассчитывались, ну а кто хотел твёрдую валюту - мы, ну я, выписывали чеки в банки на предъявителя. Никого не обманывали, так что - никто не зарезал бедного старого Сидора...\nТеперь же, народу побольше в ЗОНУ хаживать стало, рублей и не хватает для полных расчётов. Ну мы снабжаем новичков этими электронными штучками - ПДА. В них шифруется счёт и величина сбережений. Вот так то, ну а рублики.. ходят всё ещё. Можно сказать - твёрдая валюта ЗОНЫ, обеспеченная словом Торговца... </text></string>
<string id="enc_art_belt"><text>О поясе для артефактов</text></string>
<string id="enc_art_belt_text">
<text>Сидорович:\nСпрашиваешь как артефакты проявляют свои свойства? Ну... Точно то никто и не знает. Всё что мы сейчас имеем, это просто практика - кто-то, где-то, иногда случайно, иногда методом научного тыка, получил от артефакта то, что теперь называют "свойствами"... А кто был первым и не помнит уже никто. Доподлинно пока понятно одно - чтобы артефакт "включился", его нужно щёлкнуть электрической искрой. Вот от этой необходимости и возникло такое устройство, как "пояс" для артефактов. Технически, это просто реальный пояс с металлическими сетчатыми кармашками под артефакты. Сетка является одним из электродов, по другому подводится электрический потенциал от аккумуляторной батареи... Ну, как автомобильные свечи в общем. Щёлк, щёлк и... Артефакт начинает отклонять пули, позволяет переносить больший вес и т.п. А разрядится аккумулятор и всё, артефакт становится просто обычной хреновиной, хорошо если не радиоактивной...\nПояс - вещь хоть и простая, но довольно тяжёлая. Чем больше ячеек, тем тяжелее. А зачем, скажем сталкеру, который в лучшем случае найдёт один-два простеньких артефакта, таскать тяжеленный пояс на пять-шесть штук?</text></string>
<string id="belt_2_art"><text>Пояс на один артефакт</text></string>
<string id="belt_3_art"><text>Пояс на два артефакта</text></string>
<string id="belt_4_art"><text>Пояс на три артефакта</text></string>
<string id="belt_5_art"><text>Пояс на четыре артефакта</text></string>
<string id="belt_6_art"><text>Пояс для пяти артефактов</text></string>
<string id="enc_belt_2_art"><text>Пояс с металлическими сетчатыми ячейками под артефакты и отсеком для аккумулятора с электронным преобразователем для создания высокого напряжения, которое активирует артефакт.</text></string>
<string id="enc_zone_theory"><text>Что же это - Зона?</text></string>
<string id="enc_zone_theory_text">
<text>Сахаров:\nМы пытались анализировать то, с чем мы столкнулись... Теорий множество. Одни предполагают, что это всё создано кучкой не очень чистых разумом исследователей, другие - что это ответ самой Земли на то, как человечество её насилует. Моё мнение  ничем не лучше этих предположений в плане доказательств. Так... Просто туманные попытки объяснить необъяснимое.\nЛюбая теория - это только теория. И если с помощью этой теории можно вывести какие либо правила, которые подтверждаются на практике - значит эта теория имеет место быть.\nУ меня же сложилось такое мнение, что мы столкнулись с проникновением в наш мир иного. И этот другой мир, обладает своими собственными физическими законами...\nТогда всё что происходит – это не результат заговора или специального умысла, а просто взаимодействие разных физических законов нашего и другого мира. Возможно – аномалии это растения с той стороны, а монстры – это их животные. Снорки и контроллеры – это результат воздействия излучения с той стороны. Возможно роль солнечной энергии в той вселенной играет пси-энергия...\nАртефакты... Мне думается что это, так сказать, плоды аномалий. На окраинах Зоны они не "вызревают", вот и свойства имеют слабые. А ближе к центру - более "спелые", "сильные"... Самые же "вызревшие" заключены, как орехи в скорлупу - капсулу... Чтобы разрушить капсулу, необходимо магнитное поле очень высокой напряжённости - порядка тысячи гаусс...\nКонечно, это всё выглядит бредом, но бредом логичным и опирающимся на факты.</text></string>
<string id="enc_zone_teleport"><text>Про телепорты</text></string>
<string id="enc_zone_teleport_text">
<text>Фанат:\nТелепорты то? Да пёс его знает, что это и как работает. Я думаю, это типа пролома в стене в соседнюю квартиру. Хоть и неудобно, и не знаешь куда попадёшь и кого там встретишь - но зато быстро.\nПолучить телепорт, в принципе, не очень сложно - нужно просто знать "особое" место и иметь артефакт, который в этом "особом" месте позволяет проломить эту невидимую "стену". Но вот для того чтобы этот телепорт сработал так, как нужно. Для этого нужно учесть массу факторов: и время точное, и влажность воздуха, направление и силу ветра... Да ещё много чего... Не забивай голову в общем. Тут ещё и особое чутьё нужно, а уж оно никаким расчётам не подвластно...</text></string>
<string id="enc_zone_weapons"><text>Об износе оружия</text></string>
<string id="enc_zone_weapons_text">
<text>Лисапед:\nПочему износ такой у оружия? Хм... Ты присядь, налей. Да руками не тряси, прольёшь больше...\nМногие задают себе этот вопрос, я об износе. А вразумительный ответ я только от одного учёного слышал, от Васильева, Валентиныча... Хороший мужик, хоть и голован. И сталкеров не чурается, и стакан водки выкушает не морщась, и объяснит так, что становится понятно... Ну, почти понятно.\nВ общем задал я ему этот вопрос. Он говорит, что время тоже состоит из таких маленьких атомов, название тоже сказал - но извини, повторить не смогу. Эти самые атомы времени постоянно с нами, поэтому мы их и не замечаем. Ну типа как воздух. А тут, в Зоне, появились новые, не от мира нашего временные атомы. Мы их тоже почти не замечаем. Но! Покуда скорость у нас маленькая. Вроде ветра. Ну, или как будто из скоростной машины голову высунуть - всю причу растрепит...\nТы наливай, наливай...\nА у пули то - скорость ещё больше. Вот она, эта пуля, и сталкивается с другим временем гораздо больше. Стареет можно сказать на лету. Поэтому и попасть в цель больше метров двухсот в Зоне нереально... И ствол из-за скоростного пролёта пули тоже получает порцию этого "неправильного" времени. Оттого и износ дикий...\nЗабугорные вон стволы, да и наши, союзные, из новых - прямо рассыпаются от десятка выстрелов... А калашников - ничего, держится...</text></string>
<string id="enc_zone_mercenary"><text>О целях наёмников</text></string>
<string id="enc_zone_mercenary_text"><text>Волкодав:\nА! Это снова ты. Что-то слишком часто ты стал попадаться у нас на пути. Очень удобное у тебя алиби - ничего не помню, ничего не знаю. Сдаётся мне, что такой опыт не появляется на пустом месте, а? На кого работаешь? Не скажешь? Ну, ну... Успокойся. Я тоже не скажу на кого я работаю... Профессиональная этика.\nЯ к чему разговор то веду: подумай, может быть мы ищем что-то близкое - ты и я. Удобная у тебя "легенда", втихую проскользнуть везде, спросить о чём угодно, и никто и не задастся вопросом: " А почему ты тут вертишься, ищешь". Давай поможем друг другу, у меня эта Зона уже поперёк глотки стоит. Мутанты эти, аномалии, придурков со стволами, которым бы лишь бы палить... Выполнить бы быстрее задание - да и свалить к нормальной жизни, сортиру тёплому, жратве здоровой, девочкам, готовым на многое...\nЧто за задание? Хм.. Ну ладно. В общем, ты про монолитовцев слышал? Ну этих, отморозков, у которых в башке север с югом перепутаны. У них в последнее время стволы появились новые, необычные. Точность почти стопроцентная, убойность - мама не горюй! Некоторые корпорации за бугром очень бы хотели "оседлать волну" и переплюнуть конкурентов в плане поставок подобного вооружения. Но вот парадокс - ствол есть, убивает, а взять его невозможно! Даже хваталками любыми. Пытаешься его взять, а оно - пшик, и чёрный дым только... Вот мы и ищем хоть какую-то зацепку, которая позволит вынести подобное оружие из Зоны и разобрать, так сказать на запчасти. Понять принцип.\nВ общем смотри: если что то узнаешь, мы в долгу не останемся - сто лет сможешь как сыр в масле кататься, это я тебе точно говорю. 
Разгадка должна быть! Скорее всего где то там, в центре, где скопище этих "монолитовцев" - есть какое-то производство, где и собирают эти "чудопушки". Нужно только найти дорогу туда.</text></string>
<string id="enc_zone_pda"><text>О работе ПДА</text></string>
<string id="enc_zone_pda_text"><text>Доцент:\nРад видеть тебя снова. Как наши ПДА работают? Да нормально работают. В них же программка есть связи - по английски так и звучит: "Митингпойнт" - "Место встречи". Правда голосовая связь очень не устойчивая, но короткие текстовые сообщения на выбранный канал или, скажем, другую какую информацию, можно направлять. А вот то, что иногда связь действует на довольно далёкое расстояние - это уже влияние аномальности Зоны. Никто пока не разобрался в этом точно. Я же думаю, что под влиянием Выбросов локальное пространство нашего мира перемешивается с пространством мира иного. И сверхвысокие частоты, которые имеют очень маленькие длины волн, иногда проходят в разрывы между нашим и другим измерением.\nСидорович рассказывал, что когда брали опытную партию ПДА, то и не думали, что ими можно будет пользоваться для связи. Только так, для близких расчётов. Но оно вон как получилось. И теперь сталкер уже не совсем одинок в этом мире, и, иногда, может даже надеяться на помощь в критической ситуации. Ну, или последний привет передать...</text></string>
<string id="enc_zone_x16"><text>О лаборатории Х-16</text></string>
<string id="enc_zone_x16_text"><text>Выдержки из отчёта отдела ХХ ФСБ России по результатам исследования лаборатории Х-16 в аномальной Зоне ЧАЭС(Украина)\n\n...Вопросами манипулирования человеческим разумом пожалуй впервые практически занималась фашистская Германия в 37-45 годах. Имея сильную фармацевтику и радиоэлектронику, плюс неограниченное количество человеческого материала в концлагерях, фашистам удалось достичь больших успехов в создании психотропных препаратов и психотронных установок. К концу войны они были близки к внедрению параллельного сознания и создания суперагентов выполняющих заложенную программу по вербальным командам или зрительным образам. Основные работы проводились в западной Германии и результаты исследований попали в руки американцев, которые существенно развили их в годы холодной войны. В Советском союзе теоретические исследования проводились в институте мозга им.Бехтерева, а практические исследования в секретных лабораториях НКВД, КГБ и ГРУ.\n...В начале восьмидесятых создаётся лаборатория Х-16 и реализована удачная попытка создания биологической киберсистемы - искусственного мозга, где проводится моделирование поведенческих алгоритмов искусственно внедрённого параллельного сознания с принудительной блокировкой произвольных блоков памяти. Мозг испытуемого по телепатическому каналу подключали к биокомпьютеру и проводили замену личностной матрицы, изменяющей личность человека. Процедура отрабатывалась на охранниках и вольнонаемном персонале под видом медобследования, строго секретно, чтобы никто даже не догадывался об этом. И сотни спецагентов с неизвестным заданием ждут условного сигнала чтобы приступить к выполнению заложенной программы.\n...В 2012 году, во время первого выброса после аварии 1986 года, когда впервые появилась Зона, биокомпьютер, он же искусственный мозг, стал проявлять признаки  негуманоидного ксеноинтеллекта. Вначале это было воспринято с энтузиазмом, создано новое самосознание чью мощь можно использовать для получения новых знаний. Но всё обернулось не так как хотелось. Первым выявил проблему академик Патонов. В своей статье он указал на странные закономерности последствий выбросов с активностью биокомпьютера. Через месяц он при странных обстоятельствах погиб и статья не имела продолжения.\n...В 2013 году профессор Перельман доказал взаимовлияние Зоны и биокомпьютера. Тогда же было принято решение отключить биосистему. Но при  попытке отключения, персонал был подвергнут жёсткому псивоздействию и лаборатория Х-16 стала недоступна. Биокомпьютер эволюционировал в супермозг, превратившись в канал связи и возможно взаимодействия нашего мира с миром породившим Зону. Кто кого контролирует, как и кто на кого влияет неизвестно.  В настоящее время доступ в лабораторию Х-16 невозможен из-за необратимых повреждений психики человека.</text></string>
<string id="enc_flesh_mackintosh"><text>О плащах из шкур плотей</text></string>
<string id="enc_flesh_mackintosh_text"><text>Крысюк:\nУмели же в эс-се-се-ре нормальных мужиков делать... А нынешние - тьфу, и растереть... Тока о бабках и думают! Уважил ты меня, спасибо. Да я понимаю, что спасибо и не булькнет, и на шею не повесится. Есть у меня вещица одна, заветная. Костюмчик-плащик... Сечёшь? Что кривишься то? Это ж мечта любого авторитета! Простому уркагану такой плащик ночами снится. А всё почему?\nТы плоть пробовал убить? Трудно, правда? У неё, у плоти, шкура в Зоне приобрела необычные свойства, уплотняется в месте попадания пули до невероятности! Прямо броня! А вот ножиком прорезается - парадокс, мля...\nВот из этих то шкур и выделываются плащики. Есть умелец один, недалеко за оцеплением живёт. Который коричневого цвета плащик - это простенькая плоть, не сильно ещё заматеревшая. А уж чёрный... Это вообще вещь! Из самых крутых плотей! Добыть такую шкуру очень непросто! Охотники большие бабки берут за неё. Но уж если получил!\nТак что, бери и помни - Крысюк, он добро то помнит...</text></string>
<string id="enc_zone_mask_theory"><text>О защите дыхания</text></string>
<string id="enc_zone_mask_theory_text"><text>Сидорович:\nТут то у нас Кордон, окраина Зоны. Потому и опасности, на которые она богата не столь ярко себя проявляют. Так, мелочь, в общем то - немного мутантов, пара-тройка аномалий. Болт в помощь и внимательность сберегут не глупого новичка.\nДругое дело - те места, что ближе к центру. Там Зона покажет всё на что способна. Особо предупрежу - не пытайся налегке пробраться. Пока никто не уяснил что именно в воздухе может быть, но если долго дышать без средств защиты - происходит отравление. Чем спросишь? А вот не знаю! И никто не знает. Некоторые особо упёртые рискуют дышать и даже похваляются тем, что их ничего не берёт. Блаж это! Есть места, конечно, где вроде не так сильно эта зараза может повредить - вот в Баре например. Но лучше подстраховаться и там. Костюмчик с противогазом или ещё лучше - с полным циклом замкнутого дыхания, не снимать. Ну, или артефакты всякие пользительные для здоровья активировать на поясе...</text></string>
<string id="enc_zone_teleport_theory"><text>О телепортации...</text></string>
<string id="enc_zone_teleport_theory_text"><text>...микросдвиги во времени эти происходят при возникновении каждого пространственного телепорта, что вполне объяснимо, если принимать во внимание, что пространство и время неразрывны. Эти микросдвиги практически незаметны и никак не влияют на наш мир, то есть никаких нарушений причинно-следственных связей не наблюдается. Что может нам говорить о том, что обычное время жизни их составляет доли секунды, да и сами временные отклонения не превышают долей секунды. То есть это некий средний уровень. Но если имеется средний уровень дискретных состояний, то должны иметься и отклонения от нормы - флуктуации. Я полагаю, что отклонения должны приходиться примерно 1 на 100000 случаев. Расчёты этих флуктуаций я приведу позже, вычисления проделаны на основе последних данных, полученных с Агропрома и других мест, где наблюдались такие отклонения в интервале от нескольких минут до часа... \n...Исходя из этих расчётов получается, что имеется вероятность временного сдвига до 1000000 сек. вперёд или назад, то есть около двух недель. Что даже вполне могло уже где-то и произойти, но не было никем зафиксировано...\n...Это, конечно, всего лишь гипотеза, однако возникает вопрос: сколько же на самом деле должно образовываться пространственных телепортов, если такая большая вероятность флуктуационных временных отклонений? (А это именно флуктуации, ведь массово не наблюдается причинно-следственных нарушений). Судя по расчётам очень много. Конечно, подавляющее большинство существует доли секунды. Наверняка очень многие даже невозможно будет зафиксировать в ходе эксперимента. Но всё равно - их колоссально много. Из-за их количества можно даже говорить даже о неком "поле"...\n\nРукопись переданная профессором Григоровичем И.С.</text></string>

<string id="enc_dolgovjazyi_about_exo"><text>Об экзоскелетах.</text></string>
<string id="enc_dolgovjazyi_about_exo_text"><text>\nДолговязый:\nВещь конечно не из дешёвых. Ремонтируй, заряжай. И это ещё хорошо, что сейчас новое поколение пошло, износ почти целиком только при спринте на беговые сервоприводы идёт, раньше-то даже просто при ходьбе разваливались на глазах. И главное, за Периметром тестят - всё нормально, а тут - нате вам, распишитесь. Ну, зато хоть мы с Доцентом при работе всегда. Какой лучше, спрашиваешь? Да хрен его знает, кому как. Я-то вообще в эту вашу Зону не лазию, нас и здесь неплохо кормят. Мы больше с долговскими дело имеем, там в принципе просто уплотнителей побольше, от зверья, сталбыть защита максимальная. Ну оно и понятно, им по долгу службы положено зверушек изничтожать. Остальные... Обычные сталкерские очень часто с нестандартным аккумулятором приносят, там заряда где-то на пол-суток больше хватает. У "Свободы" их умельцы беговые сервоприводы чем-то обрабатывают, что их износ не так сильно берёт. Наймитские я вообще только пару раз видел, там вроде их фирменное напыление на бронешлеме и пуле-взрывозащита максимальная. Бармен как-то говорил, очень взрывозащита от какого-то монстра помогает, а какого - я не запомнил. Чё там ещё... Братки вроде как-то пытались переделывать экзы для своих делишек, но ума хватило только на то, что выдрать с мясом всю защиту и изоляцию и тем самым увеличить переносимый вес. Но их поделок я вообще давно не видел. Да и всё, вроде. Вот, как-то так.</text></string>

<string id="artmod_blood_ice_text"><text>Ломоть мяса из снежки</text></string>
<string id="artmod_mincer_meat_mosquito_bald_text"><text>Ломоть мяса из трамплина</text></string>
<string id="artmod_electra_sparkler_mosquito_bald_text"><text>Бенгальский огонь из трамплина</text></string>
<string id="artmod_ameba_slug_mosquito_bald_text"><text>Слизняк из трамплина</text></string>
<string id="artmod_cristall_mosquito_bald_text"><text>Кристалл из трамплина</text></string>
<string id="artmod_rusty_sea-urchin_mosquito_bald_text"><text>Морской ёж из трамплина</text></string>
<string id="artmod_dummy_dummy_mosquito_bald_text"><text>Пустышка из трамплина</text></string>
<string id="artmod_gravi_gravi_zone_text"><text>Грави из воронки</text></string>
<string id="artmod_ameba_slime_gravi_zone_text"><text>Слизь из воронки</text></string>
<string id="artmod_rusty_kristall_gravi_zone_text"><text>Кровь камня из воронки</text></string>
<string id="artmod_electra_flash_gravi_zone_text"><text>Вспышка из воронки</text></string>
<string id="artmod_night_star_gravi_zone_text"><text>Ночная звезда из воронки</text></string>
<string id="artmod_soul_gravi_zone_text"><text>Душа из воронки</text></string>
<string id="artmod_dummy_pellicle_gravi_zone_text"><text>Плёнка из воронки</text></string>
<string id="artmod_cristall_flower_mincer_text"><text>Каменный цветок из карусели</text></string>
<string id="artmod_drops_mincer_text"><text>Капля из карусели</text></string>
<string id="artmod_rusty_kristall_mincer_text"><text>Кристальная колючка из карусели</text></string>
<string id="artmod_electra_moonlight_mincer_text"><text>Лунный свет из карусели</text></string>
<string id="artmod_ameba_slug_mincer_text"><text>Слюда из карусели</text></string>
<string id="artmod_dummy_glassbeads_mincer_text"><text>Мамины бусы из карусели</text></string>
<string id="artmod_rusty_kristall_buzz_text"><text>Кристальная колючка из холодца</text></string>
<string id="artmod_rusty_thorn_buzz_text"><text>Колючка из холодца</text></string>
<string id="artmod_fireball_buzz_text"><text>Огненный шар из холодца</text></string>
<string id="artmod_cristall_buzz_text"><text>Кристалл из холодца</text></string>
<string id="artmod_night_star_buzz_text"><text>Золотая рыбка из холодца</text></string>
<string id="artmod_fuzz_kolobok_buzz_text"><text>Колобок из холодца</text></string>
<string id="artmod_vyvert_buzz_text"><text>Выверт из холодца</text></string>
<string id="artmod_electra_flash_zharka_text"><text>Вспышка из жарки</text></string>
<string id="artmod_ameba_slime_zharka_text"><text>Слизь из жарки</text></string>
<string id="artmod_gravi_zharka_text"><text>Грави из жарки</text></string>
<string id="artmod_night_star_zharka_text"><text>Ночная звезда из жарки</text></string>
<string id="artmod_electra_moonlight_zharka_text"><text>Лунный свет из жарки</text></string>
<string id="artmod_dummy_battery_zharka_text"><text>Батарейка из жарки</text></string>
<string id="artmod_fireball_galant_text"><text>Огненный шар из электры</text></string>
<string id="artmod_cristall_flower_galant_text"><text>Каменный цветок из электры</text></string>
<string id="artmod_ameba_mica_galant_text"><text>Слюда из электры</text></string>
<string id="artmod_electra_moonlight_galant_text"><text>Душа из электры</text></string>
<string id="artmod_gold_fish_galant_text"><text>Золотая рыбка из электры</text></string>
<string id="artmod_medusa_galant_text"><text>Медуза из электры</text></string>
<string id="artmod_dummy_spring_galant_text"><text>Пружина из электры</text></string>
<string id="artmod_glassbeads_ice_text"><text>Электробусы из снежки</text></string>
<string id="artmod_rusty_sea-urchin_ice_text"><text>Морской ёж из снежки</text></string>
<string id="artmod_ameba_slug_ice_text"><text>Слизняк из снежки</text></string>
<string id="artmod_baloon_sakbuzz_text"><text>Баллончик из киселя</text></string>

</string_table>
